django_cache_memoized/__init__.py
django_cache_memoized-0.3.dist-info/LICENSE.md
django_cache_memoized-0.3.dist-info/METADATA
django_cache_memoized-0.3.dist-info/WHEEL
django_cache_memoized-0.3.dist-info/top_level.txt
django_cache_memoized-0.3.dist-info/RECORD
