Metadata-Version: 2.1
Name: django-cache-memoized
Version: 0.3
Summary: Django decorator that can memoize any function or method to the configured Django cache
Home-page: https://github.com/bernd-wechner/django-cache-memoized
Author: Bernd Wechner
Author-email: bwechner@yahoo.com
License: UNKNOWN
Project-URL: Bug Tracker, https://github.com/bernd-wechner/django-cache-memoized/issues
Platform: UNKNOWN
Classifier: Programming Language :: Python :: 3
Classifier: License :: Freely Distributable
Classifier: Operating System :: OS Independent
Classifier: Development Status :: 4 - Beta
Classifier: Framework :: Django :: 3.2
Classifier: Intended Audience :: System Administrators
Classifier: Topic :: Software Development :: Libraries :: Python Modules
Requires-Python: >=3.6
License-File: LICENSE.md
Requires-Dist: django (>=3.2)
